LICENSE
README.md
setup.cfg
setup.py
aladhan/__init__.py
aladhan/adhan.py
aladhan/client.py
aladhan/location_types.py
aladhan.egg-info/PKG-INFO
aladhan.egg-info/SOURCES.txt
aladhan.egg-info/dependency_links.txt
aladhan.egg-info/requires.txt
aladhan.egg-info/top_level.txt